CHANGES.rst
MANIFEST.in
README.rst
setup.py
css/__init__.py
css.pure.egg-info/PKG-INFO
css.pure.egg-info/SOURCES.txt
css.pure.egg-info/dependency_links.txt
css.pure.egg-info/entry_points.txt
css.pure.egg-info/namespace_packages.txt
css.pure.egg-info/not-zip-safe
css.pure.egg-info/requires.txt
css.pure.egg-info/top_level.txt
css/pure/__init__.py
css/pure/resources/pure-min.css
css/pure/resources/pure-nr-min.css