Metadata-Version: 1.0
Name: css.pure
Version: 0.2.1
Summary: Pure CSS for Fanstatic
Home-page: https://bitbucket.org/fanstatic/js.jquery
Author: Ole Morten Halvorsen
Author-email: olemortenh@gmail.com
License: BSD
Platform: UNKNOWN
